<ROOT><BillInformation><BillNumber>HB202</BillNumber><CurrentBillString>HCS HB 202</CurrentBillString><SubstitutedBy/><Title><ShortTitle>EMPLOYMENT SECURITY</ShortTitle><LongTitle>Modifies provisions of the employment security program</LongTitle></Title><ProposedEffectiveDate>2025-08-28</ProposedEffectiveDate><CurrentLRNumber>0773H.02P</CurrentLRNumber><LastAction>05/07/2025 - SCS Voted Do Pass (S)</LastAction><NextHouseHearing>Hearing not scheduled</NextHouseHearing><Calendar>Bill currently not on a House calendar</Calendar><Action><Link>https://house.mo.gov/bill.aspx?bill=HB202&amp;year=2025&amp;code=R </Link><Description>Prefiled (H)</Description><Guid>564493</Guid><ActivitySequence>100</ActivitySequence><PubDate>2024-12-02</PubDate></Action><Action><Link>https://house.mo.gov/bill.aspx?bill=HB202&amp;year=2025&amp;code=R </Link><Description>Read First Time (H)</Description><Guid>565856</Guid><ActivitySequence>200</ActivitySequence><PubDate>2025-01-08</PubDate><HouseJournalStartPage>61</HouseJournalStartPage><HouseJournalEndPage>61</HouseJournalEndPage><JournalLink>https://documents.house.mo.gov/BillTracking/bills251/jrnpdf/jrn001.pdf#page=61</JournalLink></Action><Action><Link>https://house.mo.gov/bill.aspx?bill=HB202&amp;year=2025&amp;code=R </Link><Description>Read Second Time (H)</Description><Guid>567310</Guid><ActivitySequence>300</ActivitySequence><PubDate>2025-01-09</PubDate><HouseJournalStartPage>228</HouseJournalStartPage><HouseJournalEndPage>228</HouseJournalEndPage><JournalLink>https://documents.house.mo.gov/BillTracking/bills251/jrnpdf/jrn002.pdf#page=228</JournalLink></Action><Action><Link>https://house.mo.gov/bill.aspx?bill=HB202&amp;year=2025&amp;code=R </Link><Description>Referred: Government Efficiency(H)</Description><Guid>568531</Guid><ActivitySequence>400</ActivitySequence><PubDate>2025-01-22</PubDate><HouseJournalStartPage>370</HouseJournalStartPage><HouseJournalEndPage>370</HouseJournalEndPage><JournalLink>https://documents.house.mo.gov/BillTracking/bills251/jrnpdf/jrn009.pdf#page=370</JournalLink></Action><Action><Link>https://house.mo.gov/bill.aspx?bill=HB202&amp;year=2025&amp;code=R </Link><Description>Public Hearing Completed (H)</Description><Guid>569421</Guid><ActivitySequence>500</ActivitySequence><PubDate>2025-02-04</PubDate></Action><Action><Link>https://house.mo.gov/bill.aspx?bill=HB202&amp;year=2025&amp;code=R </Link><Description>Executive Session Completed (H)</Description><Guid>570107</Guid><ActivitySequence>600</ActivitySequence><PubDate>2025-02-11</PubDate></Action><Action><Link>https://house.mo.gov/bill.aspx?bill=HB202&amp;year=2025&amp;code=R </Link><Description>HCS Voted Do Pass (H)</Description><Guid>570110</Guid><ActivitySequence>700</ActivitySequence><PubDate>2025-02-11</PubDate></Action><Action><Link>https://house.mo.gov/bill.aspx?bill=HB202&amp;year=2025&amp;code=R </Link><Description>HCS Reported Do Pass (H)</Description><Guid>570466</Guid><ActivitySequence>800</ActivitySequence><PubDate>2025-02-17</PubDate><RollCall><TotalYes>11</TotalYes><TotalNo>6</TotalNo><TotalPresent>0</TotalPresent></RollCall><HouseJournalStartPage>651</HouseJournalStartPage><HouseJournalEndPage>651</HouseJournalEndPage><JournalLink>https://documents.house.mo.gov/BillTracking/bills251/jrnpdf/jrn023.pdf#page=651</JournalLink></Action><Action><Link>https://house.mo.gov/bill.aspx?bill=HB202&amp;year=2025&amp;code=R </Link><Description>Referred: Rules - Legislative(H)</Description><Guid>572059</Guid><ActivitySequence>900</ActivitySequence><PubDate>2025-02-26</PubDate><HouseJournalStartPage>788</HouseJournalStartPage><HouseJournalEndPage>788</HouseJournalEndPage><JournalLink>https://documents.house.mo.gov/BillTracking/bills251/jrnpdf/jrn029.pdf#page=788</JournalLink></Action><Action><Link>https://house.mo.gov/bill.aspx?bill=HB202&amp;year=2025&amp;code=R </Link><Description>Action Postponed (H)</Description><Guid>573241</Guid><ActivitySequence>1100</ActivitySequence><PubDate>2025-03-06</PubDate></Action><Action><Link>https://house.mo.gov/bill.aspx?bill=HB202&amp;year=2025&amp;code=R </Link><Description>Executive Session Completed (H)</Description><Guid>573819</Guid><ActivitySequence>1200</ActivitySequence><PubDate>2025-03-12</PubDate></Action><Action><Link>https://house.mo.gov/bill.aspx?bill=HB202&amp;year=2025&amp;code=R </Link><Description>Voted Do Pass (H)</Description><Guid>573842</Guid><ActivitySequence>1300</ActivitySequence><PubDate>2025-03-12</PubDate></Action><Action><Link>https://house.mo.gov/bill.aspx?bill=HB202&amp;year=2025&amp;code=R </Link><Description>Reported Do Pass (H)</Description><Guid>573898</Guid><ActivitySequence>1400</ActivitySequence><PubDate>2025-03-12</PubDate><RollCall><TotalYes>8</TotalYes><TotalNo>2</TotalNo><TotalPresent>0</TotalPresent></RollCall><HouseJournalStartPage>1067</HouseJournalStartPage><HouseJournalEndPage>1068</HouseJournalEndPage><JournalLink>https://documents.house.mo.gov/BillTracking/bills251/jrnpdf/jrn038.pdf#page=1067</JournalLink></Action><Action><Link>https://house.mo.gov/bill.aspx?bill=HB202&amp;year=2025&amp;code=R </Link><Description>Taken Up for Perfection (H)</Description><Guid>574697</Guid><ActivitySequence>1500</ActivitySequence><PubDate>2025-03-25</PubDate><HouseJournalStartPage>1218</HouseJournalStartPage><HouseJournalEndPage>1218</HouseJournalEndPage><JournalLink>https://documents.house.mo.gov/BillTracking/bills251/jrnpdf/jrn042.pdf#page=1218</JournalLink></Action><Action><Link>https://house.mo.gov/bill.aspx?bill=HB202&amp;year=2025&amp;code=R </Link><Description>Title of Bill - Agreed To</Description><Guid>574698</Guid><ActivitySequence>1600</ActivitySequence><PubDate>2025-03-25</PubDate><HouseJournalStartPage>1218</HouseJournalStartPage><HouseJournalEndPage>1218</HouseJournalEndPage><JournalLink>https://documents.house.mo.gov/BillTracking/bills251/jrnpdf/jrn042.pdf#page=1218</JournalLink></Action><Action><Link>https://house.mo.gov/bill.aspx?bill=HB202&amp;year=2025&amp;code=R </Link><Description>HCS Adopted (H)</Description><Guid>574699</Guid><ActivitySequence>1700</ActivitySequence><PubDate>2025-03-25</PubDate><HouseJournalStartPage>1219</HouseJournalStartPage><HouseJournalEndPage>1219</HouseJournalEndPage><JournalLink>https://documents.house.mo.gov/BillTracking/bills251/jrnpdf/jrn042.pdf#page=1219</JournalLink></Action><Action><Link>https://house.mo.gov/bill.aspx?bill=HB202&amp;year=2025&amp;code=R </Link><Description>Perfected with Amendments (H)</Description><Guid>574700</Guid><ActivitySequence>1800</ActivitySequence><PubDate>2025-03-25</PubDate><Comments>HA 1 adopted</Comments><HouseJournalStartPage>1219</HouseJournalStartPage><HouseJournalEndPage>1219</HouseJournalEndPage><JournalLink>https://documents.house.mo.gov/BillTracking/bills251/jrnpdf/jrn042.pdf#page=1219</JournalLink></Action><Action><Link>https://house.mo.gov/bill.aspx?bill=HB202&amp;year=2025&amp;code=R </Link><Description>Referred: Fiscal Review(H)</Description><Guid>574740</Guid><ActivitySequence>1900</ActivitySequence><PubDate>2025-03-26</PubDate><HouseJournalStartPage>1380</HouseJournalStartPage><HouseJournalEndPage>1380</HouseJournalEndPage><JournalLink>https://documents.house.mo.gov/BillTracking/bills251/jrnpdf/jrn043.pdf#page=1380</JournalLink></Action><Action><Link>https://house.mo.gov/bill.aspx?bill=HB202&amp;year=2025&amp;code=R </Link><Description>Executive Session Completed (H)</Description><Guid>574952</Guid><ActivitySequence>2000</ActivitySequence><PubDate>2025-03-27</PubDate></Action><Action><Link>https://house.mo.gov/bill.aspx?bill=HB202&amp;year=2025&amp;code=R </Link><Description>Voted Do Pass (H)</Description><Guid>574957</Guid><ActivitySequence>2100</ActivitySequence><PubDate>2025-03-27</PubDate></Action><Action><Link>https://house.mo.gov/bill.aspx?bill=HB202&amp;year=2025&amp;code=R </Link><Description>Reported Do Pass (H)</Description><Guid>574973</Guid><ActivitySequence>2200</ActivitySequence><PubDate>2025-03-27</PubDate><RollCall><TotalYes>5</TotalYes><TotalNo>2</TotalNo><TotalPresent>0</TotalPresent></RollCall><HouseJournalStartPage>1397</HouseJournalStartPage><HouseJournalEndPage>1397</HouseJournalEndPage><JournalLink>https://documents.house.mo.gov/BillTracking/bills251/jrnpdf/jrn044.pdf#page=1397</JournalLink></Action><Action><Link>https://house.mo.gov/bill.aspx?bill=HB202&amp;year=2025&amp;code=R </Link><Description>Taken Up for Third Reading (H)</Description><Guid>575043</Guid><ActivitySequence>2300</ActivitySequence><PubDate>2025-03-27</PubDate><HouseJournalStartPage>1413</HouseJournalStartPage><HouseJournalEndPage>1413</HouseJournalEndPage><JournalLink>https://documents.house.mo.gov/BillTracking/bills251/jrnpdf/jrn044.pdf#page=1413</JournalLink></Action><Action><Link>https://house.mo.gov/bill.aspx?bill=HB202&amp;year=2025&amp;code=R </Link><Description>Third Read and Passed (H)</Description><Guid>575044</Guid><ActivitySequence>2400</ActivitySequence><PubDate>2025-03-27</PubDate><RollCall><TotalYes>101</TotalYes><TotalNo>46</TotalNo><TotalPresent>2</TotalPresent></RollCall><HouseJournalStartPage>1413</HouseJournalStartPage><HouseJournalEndPage>1414</HouseJournalEndPage><JournalLink>https://documents.house.mo.gov/BillTracking/bills251/jrnpdf/jrn044.pdf#page=1413</JournalLink></Action><Action><Link>https://house.mo.gov/bill.aspx?bill=HB202&amp;year=2025&amp;code=R </Link><Description>Delivered to the Senate</Description><Guid>575148</Guid><ActivitySequence>2500</ActivitySequence><PubDate>2025-03-27</PubDate></Action><Action><Link>https://house.mo.gov/bill.aspx?bill=HB202&amp;year=2025&amp;code=R </Link><Description>Reported to the Senate and First Read (S)</Description><Guid>575209</Guid><ActivitySequence>2600</ActivitySequence><PubDate>2025-03-31</PubDate><SenateJournalStartPage>705</SenateJournalStartPage><SenateJournalEndPage>705</SenateJournalEndPage><JournalLink>https://www.senate.mo.gov/25info/jrnlist/default.aspx</JournalLink></Action><Action><Link>https://house.mo.gov/bill.aspx?bill=HB202&amp;year=2025&amp;code=R </Link><Description>Second read and referred: Economic and Workforce Development(S)</Description><Guid>576833</Guid><ActivitySequence>2700</ActivitySequence><PubDate>2025-04-10</PubDate><SenateJournalStartPage>798</SenateJournalStartPage><SenateJournalEndPage>798</SenateJournalEndPage><JournalLink>https://www.senate.mo.gov/25info/jrnlist/default.aspx</JournalLink></Action><Action><Link>https://house.mo.gov/bill.aspx?bill=HB202&amp;year=2025&amp;code=R </Link><Description>Public Hearing Scheduled (S)</Description><Guid>577626</Guid><ActivitySequence>2800</ActivitySequence><PubDate>2025-04-17</PubDate><Comments>Wednesday, April 23, 2025, 10:00 a.m., Senate Committee Room 1 - 1st Floor</Comments></Action><Action><Link>https://house.mo.gov/bill.aspx?bill=HB202&amp;year=2025&amp;code=R </Link><Description>Public Hearing Held (S)</Description><Guid>578000</Guid><ActivitySequence>2900</ActivitySequence><PubDate>2025-04-23</PubDate></Action><Action><Link>https://house.mo.gov/bill.aspx?bill=HB202&amp;year=2025&amp;code=R </Link><Description>Executive Session Held (S)</Description><Guid>579244</Guid><ActivitySequence>3000</ActivitySequence><PubDate>2025-05-07</PubDate></Action><Action><Link>https://house.mo.gov/bill.aspx?bill=HB202&amp;year=2025&amp;code=R </Link><Description>SCS Voted Do Pass (S)</Description><Guid>579245</Guid><ActivitySequence>3100</ActivitySequence><PubDate>2025-05-07</PubDate></Action><Amendment><AmendmentText>https://documents.house.mo.gov/billtracking/bills251/amendpdf/0773H02.01H.pdf</AmendmentText><LRNumber>0773H02.01H</LRNumber><Status>G</Status><StatusDescription>Distributed</StatusDescription><AmendmentDescription/><Sponsor>Boyko</Sponsor><AmendmentSortValue>0201HH</AmendmentSortValue></Amendment><Amendment><AmendmentText>https://documents.house.mo.gov/billtracking/bills251/amendpdf/0773H02.02H.pdf</AmendmentText><LRNumber>0773H02.02H</LRNumber><Status>A</Status><StatusDescription>Adopted</StatusDescription><AmendmentDescription>HA 1</AmendmentDescription><Sponsor>Sassmann</Sponsor><AmendmentSortValue>0202HH</AmendmentSortValue></Amendment><Amendment><AmendmentText>https://documents.house.mo.gov/billtracking/bills251/amendpdf/0773H02.03H.pdf</AmendmentText><LRNumber>0773H02.03H</LRNumber><Status>G</Status><StatusDescription>Distributed</StatusDescription><AmendmentDescription/><Sponsor>Boyko</Sponsor><AmendmentSortValue>0203HH</AmendmentSortValue></Amendment><Sponsor><SponsorType>Sponsor</SponsorType><FullName>David Casteel</FullName><District>097</District></Sponsor><Sponsor><SponsorType>Co-Sponsor</SponsorType><FullName>Danny Busick</FullName><District>003</District><CoSponsorEntryDate>2025-03-25T16:15:54.280</CoSponsorEntryDate></Sponsor><BillText><BillTextLink>https://documents.house.mo.gov/billtracking/bills251/hlrbillspdf/0773H.01I.pdf</BillTextLink><LRNumber>0773H.01I</LRNumber><DocumentName>Introduced</DocumentName><WebName>Introduced</WebName><VersionTypeCode>IN</VersionTypeCode><BillVersionSort>1</BillVersionSort></BillText><BillText><BillTextLink>https://documents.house.mo.gov/billtracking/bills251/hlrbillspdf/0773H.02C.pdf</BillTextLink><LRNumber>0773H.02C</LRNumber><DocumentName>House Committee Substitute</DocumentName><WebName>Committee</WebName><VersionTypeCode>HC</VersionTypeCode><BillVersionSort>2</BillVersionSort></BillText><BillText><BillTextLink>https://documents.house.mo.gov/billtracking/bills251/hlrbillspdf/0773H.02P.pdf</BillTextLink><LRNumber>0773H.02P</LRNumber><DocumentName>Perfected</DocumentName><WebName>Perfected</WebName><VersionTypeCode>P</VersionTypeCode><RollCalls><RollCall><RollCallPDF>https://documents.house.mo.gov/billtracking/bills251/rollcalls/044.017.pdf</RollCallPDF><SessionDay>044</SessionDay><RollCallNumber>017</RollCallNumber><TotalYes>101</TotalYes><TotalNo>46</TotalNo><TotalPresent>2</TotalPresent></RollCall></RollCalls><BillVersionSort>3</BillVersionSort></BillText><BillSummary><SummaryTextLink>https://documents.house.mo.gov/billtracking/bills251/sumpdf/HB0202I.pdf</SummaryTextLink><LRNumber>0773H.01I</LRNumber><DocumentName>Introduced</DocumentName><VersionTypeCode>IN</VersionTypeCode><BillVersionSort>1</BillVersionSort></BillSummary><BillSummary><SummaryTextLink>https://documents.house.mo.gov/billtracking/bills251/sumpdf/HB0202C.pdf</SummaryTextLink><LRNumber>0773H.02C</LRNumber><DocumentName>House Committee Substitute</DocumentName><VersionTypeCode>HC</VersionTypeCode><BillVersionSort>2</BillVersionSort></BillSummary><BillSummary><SummaryTextLink>https://documents.house.mo.gov/billtracking/bills251/sumpdf/HB0202P.pdf</SummaryTextLink><LRNumber>0773H.02P</LRNumber><DocumentName>Perfected</DocumentName><VersionTypeCode>P</VersionTypeCode><BillVersionSort>3</BillVersionSort></BillSummary><FiscalNote><FiscalNoteLink>https://documents.house.mo.gov/billtracking/bills251/fiscal/fispdf/0773H.01I.ORG.pdf</FiscalNoteLink></FiscalNote><FiscalNote><FiscalNoteLink>https://documents.house.mo.gov/billtracking/bills251/fiscal/fispdf/0773H.02C.ORG.pdf</FiscalNoteLink></FiscalNote><FiscalNote><FiscalNoteLink>https://documents.house.mo.gov/billtracking/bills251/fiscal/fispdf/0773H.02P.ORG.pdf</FiscalNoteLink></FiscalNote><Hearings><CommitteeName>Government Efficiency</CommitteeName><NoticeDate>2025-02-04</NoticeDate><NoticeTime>1900-01-01T12:00:00</NoticeTime><Location>House Hearing Room 7</Location><Comments/><AltTime/></Hearings><Hearings><CommitteeName>Government Efficiency</CommitteeName><NoticeDate>2025-02-11</NoticeDate><NoticeTime>1900-01-01T12:00:00</NoticeTime><Location>House Hearing Room 7</Location><Comments>Added HB 202.</Comments><AltTime/></Hearings><Hearings><CommitteeName>Rules - Legislative</CommitteeName><NoticeDate>2025-03-06</NoticeDate><NoticeTime>1900-01-01T00:00:00</NoticeTime><Location>House Hearing Room 7</Location><Comments>Room and time change.</Comments><AltTime>10:45 AM or upon adjournement of Rules-Administrative  (whichever is later)</AltTime></Hearings><Hearings><CommitteeName>Rules - Legislative</CommitteeName><NoticeDate>2025-03-11</NoticeDate><NoticeTime>1900-01-01T00:00:00</NoticeTime><Location>House Hearing Room 4</Location><Comments/><AltTime>10:30 AM or upon adjournment (whichever is later)</AltTime></Hearings><Hearings><CommitteeName>Rules - Legislative</CommitteeName><NoticeDate>2025-03-12</NoticeDate><NoticeTime>1900-01-01T00:00:00</NoticeTime><Location>House Hearing Room 4</Location><Comments/><AltTime>10:30 AM or upon morning recess (whichever is later)</AltTime></Hearings><Hearings><CommitteeName>Fiscal Review</CommitteeName><NoticeDate>2025-03-27</NoticeDate><NoticeTime>1900-01-01T08:30:00</NoticeTime><Location>House Hearing Room 4</Location><Comments/><AltTime/></Hearings><Witness><WitnessFormsLink>https://documents.house.mo.gov/billtracking/bills251/witnesses/HB202Testimony.pdf</WitnessFormsLink></Witness><SubjectIndex><SubjectID>061</SubjectID><SubjectName>EMPLOYEES - EMPLOYERS</SubjectName></SubjectIndex><SubjectIndex><SubjectID>062</SubjectID><SubjectName>EMPLOYMENT SECURITY</SubjectName></SubjectIndex><SubjectIndex><SubjectID>091</SubjectID><SubjectName>LABOR AND INDUSTRIAL RELATIONS, DEPARTMENT OF</SubjectName></SubjectIndex><SubjectIndex><SubjectID>234</SubjectID><SubjectName>LABOR AND MANAGEMENT</SubjectName></SubjectIndex><SubjectIndex><SubjectID>308</SubjectID><SubjectName>UNEMPLOYMENT COMPENSATION</SubjectName></SubjectIndex></BillInformation></ROOT>
