<ROOT><BillInformation><BillNumber>HJR7</BillNumber><CurrentBillString>HJR 7</CurrentBillString><SubstitutedBy/><Title><ShortTitle>GAMING REVENUES</ShortTitle><LongTitle>Proposes a constitutional amendment dividing state revenues from gaming activities between public institutions of elementary, secondary, and higher education and the administration of the Missouri veterans commission</LongTitle></Title><ProposedEffectiveDate>2025-08-28</ProposedEffectiveDate><CurrentLRNumber>0873H.01I</CurrentLRNumber><LastAction>03/11/2025 - Referred: Rules - Administrative(H)</LastAction><NextHouseHearing>Hearing not scheduled</NextHouseHearing><Calendar>Bill currently not on a House calendar</Calendar><Action><Link>https://house.mo.gov/bill.aspx?bill=HJR7&amp;year=2025&amp;code=R </Link><Description>Prefiled (H)</Description><Guid>564333</Guid><ActivitySequence>100</ActivitySequence><PubDate>2024-12-02</PubDate></Action><Action><Link>https://house.mo.gov/bill.aspx?bill=HJR7&amp;year=2025&amp;code=R </Link><Description>Read First Time (H)</Description><Guid>566414</Guid><ActivitySequence>200</ActivitySequence><PubDate>2025-01-08</PubDate><HouseJournalStartPage>50</HouseJournalStartPage><HouseJournalEndPage>50</HouseJournalEndPage><JournalLink>https://documents.house.mo.gov/BillTracking/bills251/jrnpdf/jrn001.pdf#page=50</JournalLink></Action><Action><Link>https://house.mo.gov/bill.aspx?bill=HJR7&amp;year=2025&amp;code=R </Link><Description>Read Second Time (H)</Description><Guid>567096</Guid><ActivitySequence>300</ActivitySequence><PubDate>2025-01-09</PubDate><HouseJournalStartPage>218</HouseJournalStartPage><HouseJournalEndPage>218</HouseJournalEndPage><JournalLink>https://documents.house.mo.gov/BillTracking/bills251/jrnpdf/jrn002.pdf#page=218</JournalLink></Action><Action><Link>https://house.mo.gov/bill.aspx?bill=HJR7&amp;year=2025&amp;code=R </Link><Description>Referred: Ways and Means(H)</Description><Guid>569244</Guid><ActivitySequence>400</ActivitySequence><PubDate>2025-01-30</PubDate><HouseJournalStartPage>468</HouseJournalStartPage><HouseJournalEndPage>468</HouseJournalEndPage><JournalLink>https://documents.house.mo.gov/BillTracking/bills251/jrnpdf/jrn014.pdf#page=468</JournalLink></Action><Action><Link>https://house.mo.gov/bill.aspx?bill=HJR7&amp;year=2025&amp;code=R </Link><Description>Public Hearing Completed (H)</Description><Guid>569961</Guid><ActivitySequence>500</ActivitySequence><PubDate>2025-02-10</PubDate></Action><Action><Link>https://house.mo.gov/bill.aspx?bill=HJR7&amp;year=2025&amp;code=R </Link><Description>Action Postponed (H)</Description><Guid>570619</Guid><ActivitySequence>700</ActivitySequence><PubDate>2025-02-17</PubDate></Action><Action><Link>https://house.mo.gov/bill.aspx?bill=HJR7&amp;year=2025&amp;code=R </Link><Description>Executive Session Completed (H)</Description><Guid>571549</Guid><ActivitySequence>800</ActivitySequence><PubDate>2025-02-24</PubDate></Action><Action><Link>https://house.mo.gov/bill.aspx?bill=HJR7&amp;year=2025&amp;code=R </Link><Description>Voted Do Pass (H)</Description><Guid>571555</Guid><ActivitySequence>900</ActivitySequence><PubDate>2025-02-24</PubDate></Action><Action><Link>https://house.mo.gov/bill.aspx?bill=HJR7&amp;year=2025&amp;code=R </Link><Description>Reported Do Pass (H)</Description><Guid>571702</Guid><ActivitySequence>1000</ActivitySequence><PubDate>2025-02-25</PubDate><RollCall><TotalYes>5</TotalYes><TotalNo>3</TotalNo><TotalPresent>0</TotalPresent></RollCall><HouseJournalStartPage>752</HouseJournalStartPage><HouseJournalEndPage>752</HouseJournalEndPage><JournalLink>https://documents.house.mo.gov/BillTracking/bills251/jrnpdf/jrn028.pdf#page=752</JournalLink></Action><Action><Link>https://house.mo.gov/bill.aspx?bill=HJR7&amp;year=2025&amp;code=R </Link><Description>Referred: Rules - Administrative(H)</Description><Guid>573623</Guid><ActivitySequence>1100</ActivitySequence><PubDate>2025-03-11</PubDate><HouseJournalStartPage>1039</HouseJournalStartPage><HouseJournalEndPage>1039</HouseJournalEndPage><JournalLink>https://documents.house.mo.gov/BillTracking/bills251/jrnpdf/jrn037.pdf#page=1039</JournalLink></Action><Sponsor><SponsorType>Sponsor</SponsorType><FullName>Dave Griffith</FullName><District>060</District></Sponsor><Sponsor><SponsorType>Co-Sponsor</SponsorType><FullName>Bill Lucas</FullName><District>115</District><CoSponsorEntryDate>2025-01-28T16:27:19.457</CoSponsorEntryDate></Sponsor><BillText><BillTextLink>https://documents.house.mo.gov/billtracking/bills251/hlrbillspdf/0873H.01I.pdf</BillTextLink><LRNumber>0873H.01I</LRNumber><DocumentName>Introduced</DocumentName><WebName>Introduced</WebName><VersionTypeCode>IN</VersionTypeCode><BillVersionSort>1</BillVersionSort></BillText><BillSummary><SummaryTextLink>https://documents.house.mo.gov/billtracking/bills251/sumpdf/HJR0007I.pdf</SummaryTextLink><LRNumber>0873H.01I</LRNumber><DocumentName>Introduced</DocumentName><VersionTypeCode>IN</VersionTypeCode><BillVersionSort>1</BillVersionSort></BillSummary><BillSummary><SummaryTextLink>https://documents.house.mo.gov/billtracking/bills251/sumpdf/HJR0007C.pdf</SummaryTextLink><LRNumber>0873H.01C</LRNumber><DocumentName>Committee</DocumentName><VersionTypeCode>C</VersionTypeCode><BillVersionSort>2</BillVersionSort></BillSummary><FiscalNote><FiscalNoteLink>https://documents.house.mo.gov/billtracking/bills251/fiscal/fispdf/0873H.01I.ORG.pdf</FiscalNoteLink></FiscalNote><Hearings><CommitteeName>Ways and Means</CommitteeName><NoticeDate>2025-02-10</NoticeDate><NoticeTime>1900-01-01T00:00:00</NoticeTime><Location>House Hearing Room 5</Location><Comments>Removed HB 515.</Comments><AltTime>4:30 PM or upon adjournment (whichever is later)</AltTime></Hearings><Hearings><CommitteeName>Ways and Means</CommitteeName><NoticeDate>2025-02-17</NoticeDate><NoticeTime>1900-01-01T00:00:00</NoticeTime><Location>House Hearing Room 5</Location><Comments>Removed HB 515.  Added HB 517.</Comments><AltTime>4:30 PM or upon adjournment (whichever is later)</AltTime></Hearings><Hearings><CommitteeName>Ways and Means</CommitteeName><NoticeDate>2025-02-24</NoticeDate><NoticeTime>1900-01-01T00:00:00</NoticeTime><Location>House Hearing Room 5</Location><Comments/><AltTime>4:30 PM or upon adjournment (whichever is later)</AltTime></Hearings><Witness><WitnessFormsLink>https://documents.house.mo.gov/billtracking/bills251/witnesses/HJR7Testimony.pdf</WitnessFormsLink></Witness><SubjectIndex><SubjectID>031</SubjectID><SubjectName>CONSTITUTIONAL AMENDMENTS</SubjectName></SubjectIndex><SubjectIndex><SubjectID>168</SubjectID><SubjectName>EDUCATION, ELEMENTARY AND SECONDARY</SubjectName></SubjectIndex><SubjectIndex><SubjectID>009</SubjectID><SubjectName>ENTERTAINMENT, SPORTS AND AMUSEMENTS</SubjectName></SubjectIndex><SubjectIndex><SubjectID>212</SubjectID><SubjectName>GAMBLING</SubjectName></SubjectIndex><SubjectIndex><SubjectID>152</SubjectID><SubjectName>TAXATION AND REVENUE - GENERAL</SubjectName></SubjectIndex><SubjectIndex><SubjectID>156</SubjectID><SubjectName>VETERANS</SubjectName></SubjectIndex></BillInformation></ROOT>
