<ROOT><BillInformation><BillNumber>HJR74</BillNumber><CurrentBillString>HJR 74</CurrentBillString><SubstitutedBy/><Title><ShortTitle>PROPERTY TAX EXEMPTIONS FOR CERTAIN DISABLED VETERANS</ShortTitle><LongTitle>Proposes an constitutional amendment relating to property tax exemptions for certain disabled veterans</LongTitle></Title><ProposedEffectiveDate>2025-08-28</ProposedEffectiveDate><CurrentLRNumber>2184H.01I</CurrentLRNumber><LastAction>05/15/2025 - Referred: Emerging Issues(H)</LastAction><NextHouseHearing>Hearing not scheduled</NextHouseHearing><Calendar>Bill currently not on a House calendar</Calendar><Action><Link>https://house.mo.gov/bill.aspx?bill=HJR74&amp;year=2025&amp;code=R </Link><Description>Introduced and Read First Time (H)</Description><Guid>568861</Guid><ActivitySequence>100</ActivitySequence><PubDate>2025-01-28</PubDate><HouseJournalStartPage>424</HouseJournalStartPage><HouseJournalEndPage>424</HouseJournalEndPage><JournalLink>https://documents.house.mo.gov/BillTracking/bills251/jrnpdf/jrn012.pdf#page=424</JournalLink></Action><Action><Link>https://house.mo.gov/bill.aspx?bill=HJR74&amp;year=2025&amp;code=R </Link><Description>Read Second Time (H)</Description><Guid>568936</Guid><ActivitySequence>200</ActivitySequence><PubDate>2025-01-29</PubDate><HouseJournalStartPage>448</HouseJournalStartPage><HouseJournalEndPage>448</HouseJournalEndPage><JournalLink>https://documents.house.mo.gov/BillTracking/bills251/jrnpdf/jrn013.pdf#page=448</JournalLink></Action><Action><Link>https://house.mo.gov/bill.aspx?bill=HJR74&amp;year=2025&amp;code=R </Link><Description>Referred: Emerging Issues(H)</Description><Guid>580914</Guid><ActivitySequence>300</ActivitySequence><PubDate>2025-05-15</PubDate><HouseJournalStartPage>2818</HouseJournalStartPage><HouseJournalEndPage>2818</HouseJournalEndPage><JournalLink>https://documents.house.mo.gov/BillTracking/bills251/jrnpdf/jrn072.pdf#page=2818</JournalLink></Action><Sponsor><SponsorType>Sponsor</SponsorType><FullName>Jeremy Dean</FullName><District>132</District></Sponsor><BillText><BillTextLink>https://documents.house.mo.gov/billtracking/bills251/hlrbillspdf/2184H.01I.pdf</BillTextLink><LRNumber>2184H.01I</LRNumber><DocumentName>Introduced</DocumentName><WebName>Introduced</WebName><VersionTypeCode>IN</VersionTypeCode><BillVersionSort>1</BillVersionSort></BillText><BillSummary><SummaryTextLink>https://documents.house.mo.gov/billtracking/bills251/sumpdf/HJR0074I.pdf</SummaryTextLink><LRNumber>2184H.01I</LRNumber><DocumentName>Introduced</DocumentName><VersionTypeCode>IN</VersionTypeCode><BillVersionSort>1</BillVersionSort></BillSummary><Witness/><SubjectIndex><SubjectID>031</SubjectID><SubjectName>CONSTITUTIONAL AMENDMENTS</SubjectName></SubjectIndex><SubjectIndex><SubjectID>126</SubjectID><SubjectName>PROPERTY, REAL AND PERSONAL</SubjectName></SubjectIndex><SubjectIndex><SubjectID>152</SubjectID><SubjectName>TAXATION AND REVENUE - GENERAL</SubjectName></SubjectIndex><SubjectIndex><SubjectID>270</SubjectID><SubjectName>TAXATION AND REVENUE - PROPERTY</SubjectName></SubjectIndex><SubjectIndex><SubjectID>156</SubjectID><SubjectName>VETERANS</SubjectName></SubjectIndex></BillInformation></ROOT>
