<ROOT><RepresentativeData><RepresentativeInfo><PhotoLink>https://images.house.mo.gov/MemberPhoto.aspx?id=2231</PhotoLink><LastName>Owen</LastName><FirstName>Bill</FirstName><DistrictNum>131</DistrictNum><Party>Republican</Party><YearElected>2020</YearElected><YearsServed>5</YearsServed><Hometown>Springfield</Hometown><Counties><County><CountyName>Greene</CountyName></County></Counties><Committees><Committee><CommitteeName>Financial Institutions</CommitteeName><CommitteePosition>Chair</CommitteePosition></Committee><Committee><CommitteeName>Budget</CommitteeName><CommitteePosition>Member</CommitteePosition></Committee><Committee><CommitteeName>Pensions</CommitteeName><CommitteePosition>Member</CommitteePosition></Committee><Committee><CommitteeName>Subcommittee on Appropriations - General Administration</CommitteeName><CommitteePosition>Member</CommitteePosition></Committee><Committee><CommitteeName>Subcommittee on Appropriations - Health, Mental Health, and Social Services</CommitteeName><CommitteePosition>Member</CommitteePosition></Committee></Committees><CapitolAddress>MO House of Representatives, 201 West Capitol Avenue, Room 403-A, Jefferson City MO 65101</CapitolAddress><LegislativeAssistant>John Darnall</LegislativeAssistant><PhoneNumber>573-751-2948</PhoneNumber><EmailAddress>Bill.Owen@house.mo.gov</EmailAddress><Biography>Representative Bill Owen, a Republican, represents Greene County (District 131) in the Missouri House of Representatives. He was elected to his second two-year term in November 2020.
 
Owen spent 39 years in the banking industry, and previously served in the Missouri House from 1981 -82. He sponsored the Missouri Enterprise Zone Act in 1982, and he sponsored an increase of the cigarette tax for education. 

Owen has a long history of working in his community and was named “Contributor of the Year” in 2019 by the North Springfield Betterment Association. He belongs to the First and Calvary Presbyterian Church. 

Born in Springfield, Owen attended Parkview High School before Drury University for his undergraduate degree. He also has a degree from the Graduate School of Banking at the University of Wisconsin-Madison. 

He continues to reside in Springfield with his wife, Carol. They have two children. 
</Biography></RepresentativeInfo><RepresentativeLegislation><SponsoredBill><BillType>HB</BillType><BillNumber>657</BillNumber><LegislationType>Sponsor</LegislationType><LongTitle>Modifies provisions related to proxy voting and fiduciary investment duties for certain public employee retirement and pension systems</LongTitle><LRNumber>0333H.01I</LRNumber></SponsoredBill><SponsoredBill><BillType>HB</BillType><BillNumber>739</BillNumber><LegislationType>Sponsor</LegislationType><LongTitle>Modifies provisions governing nuisance actions in home rule cities</LongTitle><LRNumber>1915H.01I</LRNumber></SponsoredBill><SponsoredBill><BillType>HB</BillType><BillNumber>809</BillNumber><LegislationType>Sponsor</LegislationType><LongTitle>Designates the "US Representative Billy Long Highway" in Greene County</LongTitle><LRNumber>2095H.01I</LRNumber></SponsoredBill><SponsoredBill><BillType>HB</BillType><BillNumber>885</BillNumber><LegislationType>Sponsor</LegislationType><LongTitle>Modifies provisions relating to continuing education requirements for certified public accountants</LongTitle><LRNumber>2110H.01I</LRNumber></SponsoredBill><SponsoredBill><BillType>HB</BillType><BillNumber>905</BillNumber><LegislationType>Sponsor</LegislationType><LongTitle>Modifies provisions relating to the retirement of certain judges</LongTitle><LRNumber>0407H.01I</LRNumber></SponsoredBill><SponsoredBill><BillType>HB</BillType><BillNumber>1007</BillNumber><LegislationType>Sponsor</LegislationType><LongTitle>Modifies provisions relating to tax credits</LongTitle><LRNumber>0763H.04C</LRNumber></SponsoredBill><SponsoredBill><BillType>HB</BillType><BillNumber>1049</BillNumber><LegislationType>Sponsor</LegislationType><LongTitle>Creates standards for credit union and banking customers to designate a trusted contact</LongTitle><LRNumber>2410H.01P</LRNumber></SponsoredBill><SponsoredBill><BillType>HB</BillType><BillNumber>1100</BillNumber><LegislationType>Sponsor</LegislationType><LongTitle>Modifies provisions for the Missouri state surplus property clearing fund</LongTitle><LRNumber>2561H.01I</LRNumber></SponsoredBill><SponsoredBill><BillType>HB</BillType><BillNumber>1155</BillNumber><LegislationType>Sponsor</LegislationType><LongTitle>Modifies provisions of the property assessment clean energy act</LongTitle><LRNumber>2641H.01I</LRNumber></SponsoredBill><SponsoredBill><BillType>HB</BillType><BillNumber>1210</BillNumber><LegislationType>Sponsor</LegislationType><LongTitle>Limits payment transaction fees for certain convenience payments</LongTitle><LRNumber>2710H.01I</LRNumber></SponsoredBill><SponsoredBill><BillType>HB</BillType><BillNumber>1257</BillNumber><LegislationType>Sponsor</LegislationType><LongTitle>Modifies the definition of "certified funds" for purposes of a statute regulating the use of certain funds by real estate settlement agents and title insurance agents</LongTitle><LRNumber>2809H.01I</LRNumber></SponsoredBill><SponsoredBill><BillType>HB</BillType><BillNumber>1258</BillNumber><LegislationType>Sponsor</LegislationType><LongTitle>Establishes a nuisance action for deteriorated property in certain counties and municipalities within those counties</LongTitle><LRNumber>2662H.01I</LRNumber></SponsoredBill><SponsoredBill><BillType>HB</BillType><BillNumber>1272</BillNumber><LegislationType>Sponsor</LegislationType><LongTitle>Modifies provisions governing contributions to qualified tuition programs</LongTitle><LRNumber>2502H.02I</LRNumber></SponsoredBill><SponsoredBill><BillType>HJR</BillType><BillNumber>44</BillNumber><LegislationType>Sponsor</LegislationType><LongTitle>Proposes a Constitutional amendment that modifies term limits for members of the general assembly </LongTitle><LRNumber>0306H.02I</LRNumber></SponsoredBill><SponsoredBill><BillType>HJR</BillType><BillNumber>65</BillNumber><LegislationType>Sponsor</LegislationType><LongTitle>Proposes a constitutional amendment changing the retirement age of judges</LongTitle><LRNumber>0402H.02I</LRNumber></SponsoredBill><SponsoredBill><BillType>HR</BillType><BillNumber>44</BillNumber><LegislationType>Sponsor</LegislationType><LongTitle>Requests certain actions be taken by the Federal Deposit Insurance Corporation so that new chartered banks are established in Missouri</LongTitle><LRNumber>0309H.02I</LRNumber></SponsoredBill><SponsoredBill><BillType>HR</BillType><BillNumber>116</BillNumber><LegislationType>Sponsor</LegislationType><LongTitle>Urges the reform or abolishment of the Consumer Financial Protection Bureau</LongTitle><LRNumber>2412H.01I</LRNumber></SponsoredBill><CoSponsoredBill><BillType>HB</BillType><BillNumber>1175</BillNumber><LegislativeType>Co-sponsor</LegislativeType><LongTitle>Reestablishes the "Second Amendment Preservation Act"</LongTitle><LRNumber>2687H.01I</LRNumber><BillSponsor>Hardwick, Bill</BillSponsor><SponsorDistrict>121</SponsorDistrict></CoSponsoredBill><SponsoredAmendment><BillType>HB</BillType><BillNumber>37</BillNumber><LegislationType>Amendment</LegislationType><LRNumber>0232H01.06H</LRNumber><AmendmentStatus>Adopted</AmendmentStatus><AmdDescription>HA 10</AmdDescription></SponsoredAmendment><SponsoredAmendment><BillType>HB</BillType><BillNumber>147</BillNumber><LegislationType>Amendment</LegislationType><LRNumber>0295H01.09H</LRNumber><AmendmentStatus>Adopted</AmendmentStatus><AmdDescription>HA 5</AmdDescription></SponsoredAmendment><SponsoredAmendment><BillType>HB</BillType><BillNumber>147</BillNumber><LegislationType>Amendment</LegislationType><LRNumber>0295H01.08H</LRNumber><AmendmentStatus>Distributed</AmendmentStatus><AmdDescription/></SponsoredAmendment><SponsoredAmendment><BillType>HB</BillType><BillNumber>326</BillNumber><LegislationType>Amendment</LegislationType><LRNumber>0745H02.07H</LRNumber><AmendmentStatus>Distributed</AmendmentStatus><AmdDescription/></SponsoredAmendment><SponsoredAmendment><BillType>HB</BillType><BillNumber>606</BillNumber><LegislationType>Amendment</LegislationType><LRNumber>1735H02.03H</LRNumber><AmendmentStatus>Adopted</AmendmentStatus><AmdDescription>HA 1</AmdDescription></SponsoredAmendment><SponsoredAmendment><BillType>HB</BillType><BillNumber>707</BillNumber><LegislationType>Amendment</LegislationType><LRNumber>1495H01.10H</LRNumber><AmendmentStatus>Adopted</AmendmentStatus><AmdDescription>HA 4</AmdDescription></SponsoredAmendment><SponsoredAmendment><BillType>HB</BillType><BillNumber>754</BillNumber><LegislationType>Amendment</LegislationType><LRNumber>1499H02.02H</LRNumber><AmendmentStatus>Adopted</AmendmentStatus><AmdDescription>HA 1, A.A.</AmdDescription></SponsoredAmendment><SponsoredAmendment><BillType>SB</BillType><BillNumber>10</BillNumber><LegislationType>Amendment</LegislationType><LRNumber>0303H09.07H</LRNumber><AmendmentStatus>Distributed</AmendmentStatus><AmdDescription/></SponsoredAmendment><SponsoredAmendment><BillType>SB</BillType><BillNumber>71</BillNumber><LegislationType>Amendment</LegislationType><LRNumber>1178H08.03H</LRNumber><AmendmentStatus>Distributed</AmendmentStatus><AmdDescription/></SponsoredAmendment><SponsoredAmendment><BillType>SB</BillType><BillNumber>97</BillNumber><LegislationType>Amendment</LegislationType><LRNumber>0676S04.04H</LRNumber><AmendmentStatus>Adopted</AmendmentStatus><AmdDescription>HA 2</AmdDescription></SponsoredAmendment><SponsoredAmendment><BillType>SB</BillType><BillNumber>97</BillNumber><LegislationType>Amendment</LegislationType><LRNumber>0676S04.05H</LRNumber><AmendmentStatus>Adopted</AmendmentStatus><AmdDescription>HA 1</AmdDescription></SponsoredAmendment><SponsoredAmendment><BillType>SB</BillType><BillNumber>97</BillNumber><LegislationType>Amendment</LegislationType><LRNumber>0676S04.02H</LRNumber><AmendmentStatus>Distributed</AmendmentStatus><AmdDescription/></SponsoredAmendment><SponsoredAmendment><BillType>SB</BillType><BillNumber>98</BillNumber><LegislationType>Amendment</LegislationType><LRNumber>0678S04.04H</LRNumber><AmendmentStatus>Adopted</AmendmentStatus><AmdDescription>HA 3</AmdDescription></SponsoredAmendment><SponsoredAmendment><BillType>SB</BillType><BillNumber>98</BillNumber><LegislationType>Amendment</LegislationType><LRNumber>0678S04.05H</LRNumber><AmendmentStatus>Adopted</AmendmentStatus><AmdDescription>HA 9</AmdDescription></SponsoredAmendment><SponsoredAmendment><BillType>SB</BillType><BillNumber>150</BillNumber><LegislationType>Amendment</LegislationType><LRNumber>0068H06.14H</LRNumber><AmendmentStatus>Defeated</AmendmentStatus><AmdDescription>HA 6</AmdDescription></SponsoredAmendment></RepresentativeLegislation></RepresentativeData></ROOT>
