<ROOT><BillInformation><BillNumber>HB1482</BillNumber><CurrentBillString>HB 1482</CurrentBillString><SubstitutedBy/><Title><ShortTitle>FUNDS FOR MEMORIALS AND MUSEUMS DEDICATED TO VETERANS</ShortTitle><LongTitle>Provides for the distribution of certain moneys for a memorial or museum dedicated to veterans in Perry County</LongTitle></Title><ProposedEffectiveDate>2025-08-28</ProposedEffectiveDate><CurrentLRNumber>3113H.01I</CurrentLRNumber><LastAction>05/15/2025 - Reported Do Pass (H)</LastAction><NextHouseHearing>Hearing not scheduled</NextHouseHearing><Calendar>Bill currently not on a House calendar</Calendar><Action><Link>https://house.mo.gov/bill.aspx?bill=HB1482&amp;year=2025&amp;code=R </Link><Description>Introduced and Read First Time (H)</Description><Guid>571927</Guid><ActivitySequence>100</ActivitySequence><PubDate>2025-02-26</PubDate><HouseJournalStartPage>765</HouseJournalStartPage><HouseJournalEndPage>765</HouseJournalEndPage><JournalLink>https://documents.house.mo.gov/BillTracking/bills251/jrnpdf/jrn029.pdf#page=765</JournalLink></Action><Action><Link>https://house.mo.gov/bill.aspx?bill=HB1482&amp;year=2025&amp;code=R </Link><Description>Read Second Time (H)</Description><Guid>572148</Guid><ActivitySequence>200</ActivitySequence><PubDate>2025-02-27</PubDate><HouseJournalStartPage>801</HouseJournalStartPage><HouseJournalEndPage>801</HouseJournalEndPage><JournalLink>https://documents.house.mo.gov/BillTracking/bills251/jrnpdf/jrn030.pdf#page=801</JournalLink></Action><Action><Link>https://house.mo.gov/bill.aspx?bill=HB1482&amp;year=2025&amp;code=R </Link><Description>Referred: Veterans and Armed Forces(H)</Description><Guid>572287</Guid><ActivitySequence>300</ActivitySequence><PubDate>2025-02-27</PubDate><HouseJournalStartPage>811</HouseJournalStartPage><HouseJournalEndPage>811</HouseJournalEndPage><JournalLink>https://documents.house.mo.gov/BillTracking/bills251/jrnpdf/jrn030.pdf#page=811</JournalLink></Action><Action><Link>https://house.mo.gov/bill.aspx?bill=HB1482&amp;year=2025&amp;code=R </Link><Description>Public Hearing Completed (H)</Description><Guid>576742</Guid><ActivitySequence>400</ActivitySequence><PubDate>2025-04-10</PubDate></Action><Action><Link>https://house.mo.gov/bill.aspx?bill=HB1482&amp;year=2025&amp;code=R </Link><Description>Executive Session Completed (H)</Description><Guid>577471</Guid><ActivitySequence>500</ActivitySequence><PubDate>2025-04-17</PubDate></Action><Action><Link>https://house.mo.gov/bill.aspx?bill=HB1482&amp;year=2025&amp;code=R </Link><Description>Voted Do Pass (H)</Description><Guid>577473</Guid><ActivitySequence>600</ActivitySequence><PubDate>2025-04-17</PubDate></Action><Action><Link>https://house.mo.gov/bill.aspx?bill=HB1482&amp;year=2025&amp;code=R </Link><Description>Reported Do Pass (H)</Description><Guid>577620</Guid><ActivitySequence>700</ActivitySequence><PubDate>2025-04-17</PubDate><RollCall><TotalYes>20</TotalYes><TotalNo>0</TotalNo><TotalPresent>0</TotalPresent></RollCall><HouseJournalStartPage>1929</HouseJournalStartPage><HouseJournalEndPage>1929</HouseJournalEndPage><JournalLink>https://documents.house.mo.gov/BillTracking/bills251/jrnpdf/jrn056.pdf#page=1929</JournalLink></Action><Action><Link>https://house.mo.gov/bill.aspx?bill=HB1482&amp;year=2025&amp;code=R </Link><Description>Referred: Rules - Administrative(H)</Description><Guid>579327</Guid><ActivitySequence>800</ActivitySequence><PubDate>2025-05-07</PubDate><HouseJournalStartPage>2534</HouseJournalStartPage><HouseJournalEndPage>2534</HouseJournalEndPage><JournalLink>https://documents.house.mo.gov/BillTracking/bills251/jrnpdf/jrn066.pdf#page=2534</JournalLink></Action><Action><Link>https://house.mo.gov/bill.aspx?bill=HB1482&amp;year=2025&amp;code=R </Link><Description>Re-referred to Committee: Rules - Legislative(H)</Description><Guid>579670</Guid><ActivitySequence>900</ActivitySequence><PubDate>2025-05-09</PubDate><HouseJournalStartPage>2714</HouseJournalStartPage><HouseJournalEndPage>2714</HouseJournalEndPage><JournalLink>https://documents.house.mo.gov/BillTracking/bills251/jrnpdf/jrn068.pdf#page=2714</JournalLink></Action><Action><Link>https://house.mo.gov/bill.aspx?bill=HB1482&amp;year=2025&amp;code=R </Link><Description>Executive Session Completed (H)</Description><Guid>579918</Guid><ActivitySequence>1000</ActivitySequence><PubDate>2025-05-15</PubDate></Action><Action><Link>https://house.mo.gov/bill.aspx?bill=HB1482&amp;year=2025&amp;code=R </Link><Description>Voted Do Pass (H)</Description><Guid>579958</Guid><ActivitySequence>1100</ActivitySequence><PubDate>2025-05-15</PubDate></Action><Action><Link>https://house.mo.gov/bill.aspx?bill=HB1482&amp;year=2025&amp;code=R </Link><Description>Reported Do Pass (H)</Description><Guid>579984</Guid><ActivitySequence>1200</ActivitySequence><PubDate>2025-05-15</PubDate><RollCall><TotalYes>5</TotalYes><TotalNo>0</TotalNo><TotalPresent>0</TotalPresent></RollCall><HouseJournalStartPage>2838</HouseJournalStartPage><HouseJournalEndPage>2838</HouseJournalEndPage><JournalLink>https://documents.house.mo.gov/BillTracking/bills251/jrnpdf/jrn072.pdf#page=2838</JournalLink></Action><Sponsor><SponsorType>Sponsor</SponsorType><FullName>Terri Violet</FullName><District>104</District></Sponsor><Sponsor><SponsorType>Co-Sponsor</SponsorType><FullName>Donna Barnes</FullName><District>028</District><CoSponsorEntryDate>2025-04-10T09:30:44.550</CoSponsorEntryDate></Sponsor><Sponsor><SponsorType>Co-Sponsor</SponsorType><FullName>Bryant Wolfin</FullName><District>145</District><CoSponsorEntryDate>2025-05-07T08:56:36.313</CoSponsorEntryDate></Sponsor><BillText><BillTextLink>https://documents.house.mo.gov/billtracking/bills251/hlrbillspdf/3113H.01I.pdf</BillTextLink><LRNumber>3113H.01I</LRNumber><DocumentName>Introduced</DocumentName><WebName>Introduced</WebName><VersionTypeCode>IN</VersionTypeCode><BillVersionSort>1</BillVersionSort></BillText><BillSummary><SummaryTextLink>https://documents.house.mo.gov/billtracking/bills251/sumpdf/HB1482I.pdf</SummaryTextLink><LRNumber>3113H.01I</LRNumber><DocumentName>Introduced</DocumentName><VersionTypeCode>IN</VersionTypeCode><BillVersionSort>1</BillVersionSort></BillSummary><BillSummary><SummaryTextLink>https://documents.house.mo.gov/billtracking/bills251/sumpdf/HB1482C.pdf</SummaryTextLink><LRNumber>3113H.01C</LRNumber><DocumentName>Committee</DocumentName><VersionTypeCode>C</VersionTypeCode><BillVersionSort>2</BillVersionSort></BillSummary><FiscalNote><FiscalNoteLink>https://documents.house.mo.gov/billtracking/bills251/fiscal/fispdf/3113H.01I.ORG.pdf</FiscalNoteLink></FiscalNote><Hearings><CommitteeName>Veterans and Armed Forces</CommitteeName><NoticeDate>2025-03-10</NoticeDate><NoticeTime>1900-01-01T00:00:00</NoticeTime><Location>House Hearing Room 1</Location><Comments/><AltTime>4:30 PM or upon adjournment (whichever is later)</AltTime></Hearings><Hearings><CommitteeName>Veterans and Armed Forces</CommitteeName><NoticeDate>2025-04-10</NoticeDate><NoticeTime>1900-01-01T08:00:00</NoticeTime><Location>House Hearing Room 7</Location><Comments>Presentations by Battle Within by Justin Hoover, Co-Founder and Executive Director and Adam Magers, Co-Founder and Clinical Manager and by Independent Living Resource Center by Susan E. Roemer, Executive Director with Independent Living Resource Center and Jim Ruedin, Executive Director with Delta Center.</Comments><AltTime/></Hearings><Hearings><CommitteeName>Veterans and Armed Forces</CommitteeName><NoticeDate>2025-04-17</NoticeDate><NoticeTime>1900-01-01T08:00:00</NoticeTime><Location>House Hearing Room 7</Location><Comments>Presentation by Independent Living Resource Center by Susan E. Roemer, Executive Director with Independent Living Resource Center and Jim Ruedin, Executive Director with Delta Center.</Comments><AltTime/></Hearings><Hearings><CommitteeName>Rules - Legislative</CommitteeName><NoticeDate>2025-05-16</NoticeDate><NoticeTime>1900-01-01T00:00:00</NoticeTime><Location>House Hearing Room 1</Location><Comments/><AltTime>9:45 AM or upon adjournment of Rules-Administrative (whichever is later)</AltTime></Hearings><Hearings><CommitteeName>Rules - Legislative</CommitteeName><NoticeDate>2025-05-15</NoticeDate><NoticeTime>1900-01-01T00:00:00</NoticeTime><Location>House Hearing Room 1</Location><Comments>Added HB 45.</Comments><AltTime>9:45 AM or upon adjournment of Rules-Administrative (whichever is later)</AltTime></Hearings><Witness><WitnessFormsLink>https://documents.house.mo.gov/billtracking/bills251/witnesses/HB1482Testimony4-10.pdf</WitnessFormsLink><WitnessFormLinkDescription>4-10</WitnessFormLinkDescription></Witness><SubjectIndex><SubjectID>109</SubjectID><SubjectName>MUSEUMS</SubjectName></SubjectIndex><SubjectIndex><SubjectID>156</SubjectID><SubjectName>VETERANS</SubjectName></SubjectIndex></BillInformation></ROOT>
